{
    "adas": {
        "spelling": "/a·das/",
        "translate": "adeh",
        "type": "nomina",
        "defenition": "tumbuhan dengan biji harum sebagai rempah",
        "function": "Untuk meredakan sakit perut dan membantu pencernaan"
    },
    "alang-alang": {
        "spelling": "/a·lang-a·lang/",
        "translate": "ilalang",
        "type": "nomina",
        "defenition": "rumput liar dengan daun tajam",
        "function": "Untuk menurunkan demam dan sebagai diuretik"
    },
    "alpukat": {
        "spelling": "/al·pu·kat/",
        "translate": "pokat",
        "type": "nomina",
        "defenition": "buah berdaging tebal berwarna hijau",
        "function": "Untuk menurunkan tekanan darah dan kolesterol"
    },
    "akar wangi": {
        "spelling": "/a•kar wa•ngi/",
        "translate": "aka wangi",
        "type": "nomina",
        "defenition": "akar beraroma dari rumput Vetiveria zizanioides",
        "function": "Untuk aromaterapi dan mengusir serangga"
    }
}